{
	"textures": [
		{
			"image": "sprites-0.png",
			"format": "RGBA8888",
			"size": {
				"w": 2048,
				"h": 2048
			},
			"scale": 1,
			"frames": [
				{
					"filename": "clouds.png",
					"rotated": false,
					"trimmed": true,
					"sourceSize": {
						"w": 544,
						"h": 240
					},
					"spriteSourceSize": {
						"x": 0,
						"y": 3,
						"w": 544,
						"h": 237
					},
					"frame": {
						"x": 1,
						"y": 1,
						"w": 544,
						"h": 237
					}
				},
				{
					"filename": "attack/Attack__006.png",
					"rotated": false,
					"trimmed": true,
					"sourceSize": {
						"w": 536,
						"h": 495
					},
					"spriteSourceSize": {
						"x": 8,
						"y": 34,
						"w": 528,
						"h": 425
					},
					"frame": {
						"x": 547,
						"y": 1,
						"w": 528,
						"h": 425
					}
				},
				{
					"filename": "attack/Attack__007.png",
					"rotated": false,
					"trimmed": true,
					"sourceSize": {
						"w": 536,
						"h": 495
					},
					"spriteSourceSize": {
						"x": 8,
						"y": 34,
						"w": 528,
						"h": 425
					},
					"frame": {
						"x": 1,
						"y": 240,
						"w": 528,
						"h": 425
					}
				},
				{
					"filename": "attack/Attack__005.png",
					"rotated": false,
					"trimmed": true,
					"sourceSize": {
						"w": 536,
						"h": 495
					},
					"spriteSourceSize": {
						"x": 8,
						"y": 33,
						"w": 528,
						"h": 422
					},
					"frame": {
						"x": 1077,
						"y": 1,
						"w": 528,
						"h": 422
					}
				},
				{
					"filename": "attack/Attack__008.png",
					"rotated": false,
					"trimmed": true,
					"sourceSize": {
						"w": 536,
						"h": 495
					},
					"spriteSourceSize": {
						"x": 13,
						"y": 30,
						"w": 418,
						"h": 424
					},
					"frame": {
						"x": 1607,
						"y": 1,
						"w": 418,
						"h": 424
					}
				},
				{
					"filename": "bg.png",
					"rotated": false,
					"trimmed": false,
					"sourceSize": {
						"w": 16,
						"h": 16
					},
					"spriteSourceSize": {
						"x": 0,
						"y": 0,
						"w": 16,
						"h": 16
					},
					"frame": {
						"x": 2027,
						"y": 1,
						"w": 16,
						"h": 16
					}
				},
				{
					"filename": "jumpAttack/Jump_Attack__007.png",
					"rotated": false,
					"trimmed": true,
					"sourceSize": {
						"w": 504,
						"h": 522
					},
					"spriteSourceSize": {
						"x": 7,
						"y": 29,
						"w": 497,
						"h": 491
					},
					"frame": {
						"x": 1077,
						"y": 425,
						"w": 497,
						"h": 491
					}
				},
				{
					"filename": "jumpAttack/Jump_Attack__003.png",
					"rotated": false,
					"trimmed": true,
					"sourceSize": {
						"w": 504,
						"h": 522
					},
					"spriteSourceSize": {
						"x": 33,
						"y": 21,
						"w": 471,
						"h": 463
					},
					"frame": {
						"x": 1576,
						"y": 427,
						"w": 471,
						"h": 463
					}
				},
				{
					"filename": "jumpAttack/Jump_Attack__004.png",
					"rotated": false,
					"trimmed": true,
					"sourceSize": {
						"w": 504,
						"h": 522
					},
					"spriteSourceSize": {
						"x": 33,
						"y": 24,
						"w": 471,
						"h": 460
					},
					"frame": {
						"x": 1576,
						"y": 892,
						"w": 471,
						"h": 460
					}
				},
				{
					"filename": "jumpAttack/Jump_Attack__006.png",
					"rotated": false,
					"trimmed": true,
					"sourceSize": {
						"w": 504,
						"h": 522
					},
					"spriteSourceSize": {
						"x": 9,
						"y": 29,
						"w": 495,
						"h": 491
					},
					"frame": {
						"x": 531,
						"y": 428,
						"w": 495,
						"h": 491
					}
				},
				{
					"filename": "Kunai.png",
					"rotated": false,
					"trimmed": false,
					"sourceSize": {
						"w": 32,
						"h": 160
					},
					"spriteSourceSize": {
						"x": 0,
						"y": 0,
						"w": 32,
						"h": 160
					},
					"frame": {
						"x": 1028,
						"y": 428,
						"w": 32,
						"h": 160
					}
				},
				{
					"filename": "attack/Attack__004.png",
					"rotated": false,
					"trimmed": true,
					"sourceSize": {
						"w": 536,
						"h": 495
					},
					"spriteSourceSize": {
						"x": 42,
						"y": 22,
						"w": 494,
						"h": 432
					},
					"frame": {
						"x": 1,
						"y": 667,
						"w": 494,
						"h": 432
					}
				},
				{
					"filename": "jumpAttack/Jump_Attack__005.png",
					"rotated": false,
					"trimmed": true,
					"sourceSize": {
						"w": 504,
						"h": 522
					},
					"spriteSourceSize": {
						"x": 14,
						"y": 29,
						"w": 490,
						"h": 491
					},
					"frame": {
						"x": 1028,
						"y": 918,
						"w": 490,
						"h": 491
					}
				},
				{
					"filename": "attack/Attack__003.png",
					"rotated": false,
					"trimmed": true,
					"sourceSize": {
						"w": 536,
						"h": 495
					},
					"spriteSourceSize": {
						"x": 46,
						"y": 14,
						"w": 490,
						"h": 440
					},
					"frame": {
						"x": 1520,
						"y": 1354,
						"w": 490,
						"h": 440
					}
				},
				{
					"filename": "glide/Glide_000.png",
					"rotated": false,
					"trimmed": true,
					"sourceSize": {
						"w": 443,
						"h": 454
					},
					"spriteSourceSize": {
						"x": 1,
						"y": 18,
						"w": 413,
						"h": 432
					},
					"frame": {
						"x": 497,
						"y": 921,
						"w": 413,
						"h": 432
					}
				},
				{
					"filename": "sky.png",
					"rotated": false,
					"trimmed": false,
					"sourceSize": {
						"w": 112,
						"h": 304
					},
					"spriteSourceSize": {
						"x": 0,
						"y": 0,
						"w": 112,
						"h": 304
					},
					"frame": {
						"x": 912,
						"y": 921,
						"w": 112,
						"h": 304
					}
				},
				{
					"filename": "sea.png",
					"rotated": false,
					"trimmed": false,
					"sourceSize": {
						"w": 112,
						"h": 96
					},
					"spriteSourceSize": {
						"x": 0,
						"y": 0,
						"w": 112,
						"h": 96
					},
					"frame": {
						"x": 912,
						"y": 1227,
						"w": 112,
						"h": 96
					}
				},
				{
					"filename": "glide/Glide_001.png",
					"rotated": false,
					"trimmed": true,
					"sourceSize": {
						"w": 443,
						"h": 454
					},
					"spriteSourceSize": {
						"x": 0,
						"y": 18,
						"w": 413,
						"h": 430
					},
					"frame": {
						"x": 1,
						"y": 1101,
						"w": 413,
						"h": 430
					}
				},
				{
					"filename": "glide/Glide_009.png",
					"rotated": false,
					"trimmed": true,
					"sourceSize": {
						"w": 443,
						"h": 454
					},
					"spriteSourceSize": {
						"x": 0,
						"y": 18,
						"w": 413,
						"h": 430
					},
					"frame": {
						"x": 1,
						"y": 1533,
						"w": 413,
						"h": 430
					}
				},
				{
					"filename": "glide/Glide_002.png",
					"rotated": false,
					"trimmed": true,
					"sourceSize": {
						"w": 443,
						"h": 454
					},
					"spriteSourceSize": {
						"x": 0,
						"y": 17,
						"w": 412,
						"h": 429
					},
					"frame": {
						"x": 416,
						"y": 1355,
						"w": 412,
						"h": 429
					}
				},
				{
					"filename": "glide/Glide_008.png",
					"rotated": false,
					"trimmed": true,
					"sourceSize": {
						"w": 443,
						"h": 454
					},
					"spriteSourceSize": {
						"x": 0,
						"y": 17,
						"w": 412,
						"h": 429
					},
					"frame": {
						"x": 830,
						"y": 1411,
						"w": 412,
						"h": 429
					}
				}
			]
		},
		{
			"image": "sprites-1.png",
			"format": "RGBA8888",
			"size": {
				"w": 2048,
				"h": 2048
			},
			"scale": 1,
			"frames": [
				{
					"filename": "glide/Glide_003.png",
					"rotated": false,
					"trimmed": true,
					"sourceSize": {
						"w": 443,
						"h": 454
					},
					"spriteSourceSize": {
						"x": 0,
						"y": 15,
						"w": 411,
						"h": 429
					},
					"frame": {
						"x": 1,
						"y": 1,
						"w": 411,
						"h": 429
					}
				},
				{
					"filename": "glide/Glide_004.png",
					"rotated": false,
					"trimmed": true,
					"sourceSize": {
						"w": 443,
						"h": 454
					},
					"spriteSourceSize": {
						"x": 0,
						"y": 13,
						"w": 411,
						"h": 429
					},
					"frame": {
						"x": 1,
						"y": 432,
						"w": 411,
						"h": 429
					}
				},
				{
					"filename": "glide/Glide_006.png",
					"rotated": false,
					"trimmed": true,
					"sourceSize": {
						"w": 443,
						"h": 454
					},
					"spriteSourceSize": {
						"x": 0,
						"y": 13,
						"w": 411,
						"h": 429
					},
					"frame": {
						"x": 1,
						"y": 863,
						"w": 411,
						"h": 429
					}
				},
				{
					"filename": "glide/Glide_007.png",
					"rotated": false,
					"trimmed": true,
					"sourceSize": {
						"w": 443,
						"h": 454
					},
					"spriteSourceSize": {
						"x": 0,
						"y": 15,
						"w": 411,
						"h": 429
					},
					"frame": {
						"x": 1,
						"y": 1294,
						"w": 411,
						"h": 429
					}
				},
				{
					"filename": "dead/Dead__004.png",
					"rotated": false,
					"trimmed": true,
					"sourceSize": {
						"w": 482,
						"h": 498
					},
					"spriteSourceSize": {
						"x": 17,
						"y": 179,
						"w": 419,
						"h": 300
					},
					"frame": {
						"x": 1,
						"y": 1725,
						"w": 419,
						"h": 300
					}
				},
				{
					"filename": "glide/Glide_005.png",
					"rotated": false,
					"trimmed": true,
					"sourceSize": {
						"w": 443,
						"h": 454
					},
					"spriteSourceSize": {
						"x": 0,
						"y": 12,
						"w": 410,
						"h": 428
					},
					"frame": {
						"x": 414,
						"y": 1,
						"w": 410,
						"h": 428
					}
				},
				{
					"filename": "attack/Attack__009.png",
					"rotated": false,
					"trimmed": true,
					"sourceSize": {
						"w": 536,
						"h": 495
					},
					"spriteSourceSize": {
						"x": 41,
						"y": 23,
						"w": 383,
						"h": 432
					},
					"frame": {
						"x": 414,
						"y": 431,
						"w": 383,
						"h": 432
					}
				},
				{
					"filename": "jumpAttack/Jump_Attack__008.png",
					"rotated": false,
					"trimmed": true,
					"sourceSize": {
						"w": 504,
						"h": 522
					},
					"spriteSourceSize": {
						"x": 12,
						"y": 24,
						"w": 340,
						"h": 464
					},
					"frame": {
						"x": 414,
						"y": 865,
						"w": 340,
						"h": 464
					}
				},
				{
					"filename": "dead/Dead__003.png",
					"rotated": false,
					"trimmed": true,
					"sourceSize": {
						"w": 482,
						"h": 498
					},
					"spriteSourceSize": {
						"x": 25,
						"y": 120,
						"w": 379,
						"h": 370
					},
					"frame": {
						"x": 414,
						"y": 1331,
						"w": 379,
						"h": 370
					}
				},
				{
					"filename": "dead/Dead__005.png",
					"rotated": false,
					"trimmed": true,
					"sourceSize": {
						"w": 482,
						"h": 498
					},
					"spriteSourceSize": {
						"x": 15,
						"y": 202,
						"w": 436,
						"h": 281
					},
					"frame": {
						"x": 422,
						"y": 1703,
						"w": 436,
						"h": 281
					}
				},
				{
					"filename": "jumpAttack/Jump_Attack__009.png",
					"rotated": false,
					"trimmed": true,
					"sourceSize": {
						"w": 504,
						"h": 522
					},
					"spriteSourceSize": {
						"x": 33,
						"y": 19,
						"w": 376,
						"h": 411
					},
					"frame": {
						"x": 756,
						"y": 865,
						"w": 376,
						"h": 411
					}
				},
				{
					"filename": "run/Run__003.png",
					"rotated": false,
					"trimmed": true,
					"sourceSize": {
						"w": 363,
						"h": 458
					},
					"spriteSourceSize": {
						"x": 0,
						"y": 7,
						"w": 352,
						"h": 422
					},
					"frame": {
						"x": 795,
						"y": 1278,
						"w": 352,
						"h": 422
					}
				},
				{
					"filename": "slide/Slide__000.png",
					"rotated": false,
					"trimmed": true,
					"sourceSize": {
						"w": 373,
						"h": 351
					},
					"spriteSourceSize": {
						"x": 7,
						"y": 2,
						"w": 366,
						"h": 345
					},
					"frame": {
						"x": 860,
						"y": 1702,
						"w": 366,
						"h": 345
					}
				},
				{
					"filename": "run/Run__004.png",
					"rotated": false,
					"trimmed": true,
					"sourceSize": {
						"w": 363,
						"h": 458
					},
					"spriteSourceSize": {
						"x": 7,
						"y": 14,
						"w": 354,
						"h": 427
					},
					"frame": {
						"x": 799,
						"y": 431,
						"w": 354,
						"h": 427
					}
				},
				{
					"filename": "jumpThrow/Jump_Throw__005.png",
					"rotated": false,
					"trimmed": true,
					"sourceSize": {
						"w": 360,
						"h": 431
					},
					"spriteSourceSize": {
						"x": 7,
						"y": 17,
						"w": 353,
						"h": 401
					},
					"frame": {
						"x": 1134,
						"y": 860,
						"w": 353,
						"h": 401
					}
				},
				{
					"filename": "dead/Dead__002.png",
					"rotated": false,
					"trimmed": true,
					"sourceSize": {
						"w": 482,
						"h": 498
					},
					"spriteSourceSize": {
						"x": 10,
						"y": 66,
						"w": 336,
						"h": 432
					},
					"frame": {
						"x": 1149,
						"y": 1263,
						"w": 336,
						"h": 432
					}
				},
				{
					"filename": "slide/Slide__002.png",
					"rotated": false,
					"trimmed": true,
					"sourceSize": {
						"w": 373,
						"h": 351
					},
					"spriteSourceSize": {
						"x": 10,
						"y": 1,
						"w": 363,
						"h": 347
					},
					"frame": {
						"x": 1228,
						"y": 1697,
						"w": 363,
						"h": 347
					}
				},
				{
					"filename": "jumpThrow/Jump_Throw__006.png",
					"rotated": false,
					"trimmed": true,
					"sourceSize": {
						"w": 360,
						"h": 431
					},
					"spriteSourceSize": {
						"x": 9,
						"y": 17,
						"w": 351,
						"h": 401
					},
					"frame": {
						"x": 1487,
						"y": 1263,
						"w": 351,
						"h": 401
					}
				},
				{
					"filename": "slide/Slide__008.png",
					"rotated": false,
					"trimmed": true,
					"sourceSize": {
						"w": 373,
						"h": 351
					},
					"spriteSourceSize": {
						"x": 10,
						"y": 1,
						"w": 363,
						"h": 347
					},
					"frame": {
						"x": 1593,
						"y": 1666,
						"w": 363,
						"h": 347
					}
				},
				{
					"filename": "run/Run__005.png",
					"rotated": false,
					"trimmed": true,
					"sourceSize": {
						"w": 363,
						"h": 458
					},
					"spriteSourceSize": {
						"x": 33,
						"y": 14,
						"w": 328,
						"h": 427
					},
					"frame": {
						"x": 826,
						"y": 1,
						"w": 328,
						"h": 427
					}
				},
				{
					"filename": "jumpThrow/Jump_Throw__004.png",
					"rotated": false,
					"trimmed": true,
					"sourceSize": {
						"w": 360,
						"h": 431
					},
					"spriteSourceSize": {
						"x": 14,
						"y": 17,
						"w": 346,
						"h": 401
					},
					"frame": {
						"x": 1155,
						"y": 430,
						"w": 346,
						"h": 401
					}
				},
				{
					"filename": "run/Run__009.png",
					"rotated": false,
					"trimmed": true,
					"sourceSize": {
						"w": 363,
						"h": 458
					},
					"spriteSourceSize": {
						"x": 33,
						"y": 14,
						"w": 328,
						"h": 422
					},
					"frame": {
						"x": 1489,
						"y": 833,
						"w": 328,
						"h": 422
					}
				},
				{
					"filename": "idle/Idle__004.png",
					"rotated": false,
					"trimmed": true,
					"sourceSize": {
						"w": 232,
						"h": 439
					},
					"spriteSourceSize": {
						"x": 4,
						"y": 2,
						"w": 228,
						"h": 437
					},
					"frame": {
						"x": 1819,
						"y": 1,
						"w": 228,
						"h": 437
					}
				},
				{
					"filename": "idle/Idle__006.png",
					"rotated": false,
					"trimmed": true,
					"sourceSize": {
						"w": 232,
						"h": 439
					},
					"spriteSourceSize": {
						"x": 4,
						"y": 2,
						"w": 228,
						"h": 437
					},
					"frame": {
						"x": 1819,
						"y": 1,
						"w": 228,
						"h": 437
					}
				},
				{
					"filename": "slide/Slide__001.png",
					"rotated": false,
					"trimmed": true,
					"sourceSize": {
						"w": 373,
						"h": 351
					},
					"spriteSourceSize": {
						"x": 9,
						"y": 2,
						"w": 364,
						"h": 345
					},
					"frame": {
						"x": 1503,
						"y": 440,
						"w": 364,
						"h": 345
					}
				},
				{
					"filename": "idle/Idle__005.png",
					"rotated": false,
					"trimmed": true,
					"sourceSize": {
						"w": 232,
						"h": 439
					},
					"spriteSourceSize": {
						"x": 5,
						"y": 3,
						"w": 227,
						"h": 436
					},
					"frame": {
						"x": 1819,
						"y": 787,
						"w": 227,
						"h": 436
					}
				},
				{
					"filename": "jump/Jump__007.png",
					"rotated": false,
					"trimmed": true,
					"sourceSize": {
						"w": 362,
						"h": 483
					},
					"spriteSourceSize": {
						"x": 20,
						"y": 16,
						"w": 303,
						"h": 422
					},
					"frame": {
						"x": 1503,
						"y": 1,
						"w": 303,
						"h": 422
					}
				},
				{
					"filename": "jump/Jump__008.png",
					"rotated": false,
					"trimmed": true,
					"sourceSize": {
						"w": 362,
						"h": 483
					},
					"spriteSourceSize": {
						"x": 5,
						"y": 16,
						"w": 331,
						"h": 414
					},
					"frame": {
						"x": 1156,
						"y": 1,
						"w": 331,
						"h": 414
					}
				},
				{
					"filename": "jump/Jump__009.png",
					"rotated": false,
					"trimmed": true,
					"sourceSize": {
						"w": 362,
						"h": 483
					},
					"spriteSourceSize": {
						"x": 5,
						"y": 16,
						"w": 331,
						"h": 414
					},
					"frame": {
						"x": 1156,
						"y": 1,
						"w": 331,
						"h": 414
					}
				}
			]
		},
		{
			"image": "sprites-2.png",
			"format": "RGBA8888",
			"size": {
				"w": 2048,
				"h": 2048
			},
			"scale": 1,
			"frames": [
				{
					"filename": "run/Run__001.png",
					"rotated": false,
					"trimmed": true,
					"sourceSize": {
						"w": 363,
						"h": 458
					},
					"spriteSourceSize": {
						"x": 31,
						"y": 8,
						"w": 323,
						"h": 450
					},
					"frame": {
						"x": 1,
						"y": 1,
						"w": 323,
						"h": 450
					}
				},
				{
					"filename": "run/Run__006.png",
					"rotated": false,
					"trimmed": true,
					"sourceSize": {
						"w": 363,
						"h": 458
					},
					"spriteSourceSize": {
						"x": 30,
						"y": 8,
						"w": 323,
						"h": 448
					},
					"frame": {
						"x": 1,
						"y": 453,
						"w": 323,
						"h": 448
					}
				},
				{
					"filename": "throw/Throw__007.png",
					"rotated": false,
					"trimmed": true,
					"sourceSize": {
						"w": 377,
						"h": 451
					},
					"spriteSourceSize": {
						"x": 44,
						"y": 4,
						"w": 325,
						"h": 447
					},
					"frame": {
						"x": 1,
						"y": 903,
						"w": 325,
						"h": 447
					}
				},
				{
					"filename": "run/Run__002.png",
					"rotated": false,
					"trimmed": true,
					"sourceSize": {
						"w": 363,
						"h": 458
					},
					"spriteSourceSize": {
						"x": 27,
						"y": 4,
						"w": 321,
						"h": 446
					},
					"frame": {
						"x": 1,
						"y": 1352,
						"w": 321,
						"h": 446
					}
				},
				{
					"filename": "throw/Throw__002.png",
					"rotated": false,
					"trimmed": true,
					"sourceSize": {
						"w": 377,
						"h": 451
					},
					"spriteSourceSize": {
						"x": 48,
						"y": 4,
						"w": 316,
						"h": 446
					},
					"frame": {
						"x": 324,
						"y": 1352,
						"w": 316,
						"h": 446
					}
				},
				{
					"filename": "throw/Throw__003.png",
					"rotated": false,
					"trimmed": true,
					"sourceSize": {
						"w": 377,
						"h": 451
					},
					"spriteSourceSize": {
						"x": 7,
						"y": 4,
						"w": 305,
						"h": 445
					},
					"frame": {
						"x": 326,
						"y": 1,
						"w": 305,
						"h": 445
					}
				},
				{
					"filename": "throw/Throw__004.png",
					"rotated": false,
					"trimmed": true,
					"sourceSize": {
						"w": 377,
						"h": 451
					},
					"spriteSourceSize": {
						"x": 10,
						"y": 4,
						"w": 301,
						"h": 445
					},
					"frame": {
						"x": 326,
						"y": 448,
						"w": 301,
						"h": 445
					}
				},
				{
					"filename": "throw/Throw__005.png",
					"rotated": false,
					"trimmed": true,
					"sourceSize": {
						"w": 377,
						"h": 451
					},
					"spriteSourceSize": {
						"x": 12,
						"y": 4,
						"w": 299,
						"h": 445
					},
					"frame": {
						"x": 328,
						"y": 895,
						"w": 299,
						"h": 445
					}
				},
				{
					"filename": "throw/Throw__008.png",
					"rotated": false,
					"trimmed": true,
					"sourceSize": {
						"w": 377,
						"h": 451
					},
					"spriteSourceSize": {
						"x": 74,
						"y": 6,
						"w": 294,
						"h": 445
					},
					"frame": {
						"x": 629,
						"y": 448,
						"w": 294,
						"h": 445
					}
				},
				{
					"filename": "throw/Throw__006.png",
					"rotated": false,
					"trimmed": true,
					"sourceSize": {
						"w": 377,
						"h": 451
					},
					"spriteSourceSize": {
						"x": 15,
						"y": 4,
						"w": 297,
						"h": 444
					},
					"frame": {
						"x": 633,
						"y": 1,
						"w": 297,
						"h": 444
					}
				},
				{
					"filename": "attack/Attack__002.png",
					"rotated": false,
					"trimmed": true,
					"sourceSize": {
						"w": 536,
						"h": 495
					},
					"spriteSourceSize": {
						"x": 17,
						"y": 13,
						"w": 298,
						"h": 441
					},
					"frame": {
						"x": 629,
						"y": 895,
						"w": 298,
						"h": 441
					}
				},
				{
					"filename": "jump/Jump__000.png",
					"rotated": false,
					"trimmed": true,
					"sourceSize": {
						"w": 362,
						"h": 483
					},
					"spriteSourceSize": {
						"x": 62,
						"y": 30,
						"w": 284,
						"h": 439
					},
					"frame": {
						"x": 925,
						"y": 447,
						"w": 284,
						"h": 439
					}
				},
				{
					"filename": "attack/Attack__000.png",
					"rotated": false,
					"trimmed": true,
					"sourceSize": {
						"w": 536,
						"h": 495
					},
					"spriteSourceSize": {
						"x": 46,
						"y": 18,
						"w": 288,
						"h": 437
					},
					"frame": {
						"x": 932,
						"y": 1,
						"w": 288,
						"h": 437
					}
				},
				{
					"filename": "run/Run__000.png",
					"rotated": false,
					"trimmed": true,
					"sourceSize": {
						"w": 363,
						"h": 458
					},
					"spriteSourceSize": {
						"x": 33,
						"y": 14,
						"w": 328,
						"h": 433
					},
					"frame": {
						"x": 642,
						"y": 1338,
						"w": 328,
						"h": 433
					}
				},
				{
					"filename": "dead/Dead__006.png",
					"rotated": false,
					"trimmed": true,
					"sourceSize": {
						"w": 482,
						"h": 498
					},
					"spriteSourceSize": {
						"x": 8,
						"y": 222,
						"w": 442,
						"h": 259
					},
					"frame": {
						"x": 642,
						"y": 1773,
						"w": 442,
						"h": 259
					}
				},
				{
					"filename": "dead/Dead__007.png",
					"rotated": false,
					"trimmed": true,
					"sourceSize": {
						"w": 482,
						"h": 498
					},
					"spriteSourceSize": {
						"x": 8,
						"y": 222,
						"w": 442,
						"h": 259
					},
					"frame": {
						"x": 642,
						"y": 1773,
						"w": 442,
						"h": 259
					}
				},
				{
					"filename": "dead/Dead__008.png",
					"rotated": false,
					"trimmed": true,
					"sourceSize": {
						"w": 482,
						"h": 498
					},
					"spriteSourceSize": {
						"x": 8,
						"y": 222,
						"w": 442,
						"h": 259
					},
					"frame": {
						"x": 642,
						"y": 1773,
						"w": 442,
						"h": 259
					}
				},
				{
					"filename": "dead/Dead__009.png",
					"rotated": false,
					"trimmed": true,
					"sourceSize": {
						"w": 482,
						"h": 498
					},
					"spriteSourceSize": {
						"x": 8,
						"y": 222,
						"w": 442,
						"h": 259
					},
					"frame": {
						"x": 642,
						"y": 1773,
						"w": 442,
						"h": 259
					}
				},
				{
					"filename": "run/Run__007.png",
					"rotated": false,
					"trimmed": true,
					"sourceSize": {
						"w": 363,
						"h": 458
					},
					"spriteSourceSize": {
						"x": 28,
						"y": 4,
						"w": 316,
						"h": 431
					},
					"frame": {
						"x": 929,
						"y": 888,
						"w": 316,
						"h": 431
					}
				},
				{
					"filename": "jumpThrow/Jump_Throw__009.png",
					"rotated": false,
					"trimmed": true,
					"sourceSize": {
						"w": 360,
						"h": 431
					},
					"spriteSourceSize": {
						"x": 49,
						"y": 14,
						"w": 302,
						"h": 414
					},
					"frame": {
						"x": 1211,
						"y": 440,
						"w": 302,
						"h": 414
					}
				},
				{
					"filename": "jumpThrow/Jump_Throw__008.png",
					"rotated": false,
					"trimmed": true,
					"sourceSize": {
						"w": 360,
						"h": 431
					},
					"spriteSourceSize": {
						"x": 49,
						"y": 15,
						"w": 305,
						"h": 408
					},
					"frame": {
						"x": 1222,
						"y": 1,
						"w": 305,
						"h": 408
					}
				},
				{
					"filename": "run/Run__008.png",
					"rotated": false,
					"trimmed": true,
					"sourceSize": {
						"w": 363,
						"h": 458
					},
					"spriteSourceSize": {
						"x": 29,
						"y": 6,
						"w": 318,
						"h": 405
					},
					"frame": {
						"x": 972,
						"y": 1321,
						"w": 318,
						"h": 405
					}
				},
				{
					"filename": "jumpThrow/Jump_Throw__007.png",
					"rotated": false,
					"trimmed": true,
					"sourceSize": {
						"w": 360,
						"h": 431
					},
					"spriteSourceSize": {
						"x": 34,
						"y": 16,
						"w": 323,
						"h": 402
					},
					"frame": {
						"x": 1247,
						"y": 856,
						"w": 323,
						"h": 402
					}
				},
				{
					"filename": "jumpThrow/Jump_Throw__003.png",
					"rotated": false,
					"trimmed": true,
					"sourceSize": {
						"w": 360,
						"h": 431
					},
					"spriteSourceSize": {
						"x": 21,
						"y": 17,
						"w": 339,
						"h": 401
					},
					"frame": {
						"x": 1515,
						"y": 411,
						"w": 339,
						"h": 401
					}
				},
				{
					"filename": "slide/Slide__004.png",
					"rotated": false,
					"trimmed": true,
					"sourceSize": {
						"w": 373,
						"h": 351
					},
					"spriteSourceSize": {
						"x": 15,
						"y": 1,
						"w": 358,
						"h": 348
					},
					"frame": {
						"x": 1529,
						"y": 1,
						"w": 358,
						"h": 348
					}
				},
				{
					"filename": "slide/Slide__009.png",
					"rotated": false,
					"trimmed": true,
					"sourceSize": {
						"w": 373,
						"h": 351
					},
					"spriteSourceSize": {
						"x": 9,
						"y": 2,
						"w": 364,
						"h": 345
					},
					"frame": {
						"x": 1572,
						"y": 814,
						"w": 364,
						"h": 345
					}
				},
				{
					"filename": "slide/Slide__003.png",
					"rotated": false,
					"trimmed": true,
					"sourceSize": {
						"w": 373,
						"h": 351
					},
					"spriteSourceSize": {
						"x": 12,
						"y": 1,
						"w": 361,
						"h": 347
					},
					"frame": {
						"x": 1572,
						"y": 1161,
						"w": 361,
						"h": 347
					}
				},
				{
					"filename": "slide/Slide__006.png",
					"rotated": false,
					"trimmed": true,
					"sourceSize": {
						"w": 373,
						"h": 351
					},
					"spriteSourceSize": {
						"x": 15,
						"y": 1,
						"w": 358,
						"h": 348
					},
					"frame": {
						"x": 1292,
						"y": 1510,
						"w": 358,
						"h": 348
					}
				},
				{
					"filename": "slide/Slide__007.png",
					"rotated": false,
					"trimmed": true,
					"sourceSize": {
						"w": 373,
						"h": 351
					},
					"spriteSourceSize": {
						"x": 12,
						"y": 1,
						"w": 361,
						"h": 347
					},
					"frame": {
						"x": 1652,
						"y": 1510,
						"w": 361,
						"h": 347
					}
				}
			]
		},
		{
			"image": "sprites-3.png",
			"format": "RGBA8888",
			"size": {
				"w": 2048,
				"h": 2048
			},
			"scale": 1,
			"frames": [
				{
					"filename": "jump/Jump__001.png",
					"rotated": false,
					"trimmed": true,
					"sourceSize": {
						"w": 362,
						"h": 483
					},
					"spriteSourceSize": {
						"x": 54,
						"y": 20,
						"w": 268,
						"h": 463
					},
					"frame": {
						"x": 1,
						"y": 1,
						"w": 268,
						"h": 463
					}
				},
				{
					"filename": "climb/Climb_005.png",
					"rotated": false,
					"trimmed": true,
					"sourceSize": {
						"w": 282,
						"h": 464
					},
					"spriteSourceSize": {
						"x": 30,
						"y": 2,
						"w": 235,
						"h": 462
					},
					"frame": {
						"x": 1,
						"y": 466,
						"w": 235,
						"h": 462
					}
				},
				{
					"filename": "climb/Climb_000.png",
					"rotated": false,
					"trimmed": true,
					"sourceSize": {
						"w": 282,
						"h": 464
					},
					"spriteSourceSize": {
						"x": 7,
						"y": 2,
						"w": 234,
						"h": 461
					},
					"frame": {
						"x": 1,
						"y": 930,
						"w": 234,
						"h": 461
					}
				},
				{
					"filename": "climb/Climb_001.png",
					"rotated": false,
					"trimmed": true,
					"sourceSize": {
						"w": 282,
						"h": 464
					},
					"spriteSourceSize": {
						"x": 3,
						"y": 2,
						"w": 256,
						"h": 457
					},
					"frame": {
						"x": 1,
						"y": 1393,
						"w": 256,
						"h": 457
					}
				},
				{
					"filename": "climb/Climb_009.png",
					"rotated": false,
					"trimmed": true,
					"sourceSize": {
						"w": 282,
						"h": 464
					},
					"spriteSourceSize": {
						"x": 3,
						"y": 2,
						"w": 256,
						"h": 457
					},
					"frame": {
						"x": 237,
						"y": 930,
						"w": 256,
						"h": 457
					}
				},
				{
					"filename": "climb/Climb_004.png",
					"rotated": false,
					"trimmed": true,
					"sourceSize": {
						"w": 282,
						"h": 464
					},
					"spriteSourceSize": {
						"x": 19,
						"y": 2,
						"w": 256,
						"h": 456
					},
					"frame": {
						"x": 238,
						"y": 466,
						"w": 256,
						"h": 456
					}
				},
				{
					"filename": "climb/Climb_006.png",
					"rotated": false,
					"trimmed": true,
					"sourceSize": {
						"w": 282,
						"h": 464
					},
					"spriteSourceSize": {
						"x": 19,
						"y": 2,
						"w": 256,
						"h": 456
					},
					"frame": {
						"x": 271,
						"y": 1,
						"w": 256,
						"h": 456
					}
				},
				{
					"filename": "climb/Climb_002.png",
					"rotated": false,
					"trimmed": true,
					"sourceSize": {
						"w": 282,
						"h": 464
					},
					"spriteSourceSize": {
						"x": 1,
						"y": 2,
						"w": 271,
						"h": 450
					},
					"frame": {
						"x": 259,
						"y": 1389,
						"w": 271,
						"h": 450
					}
				},
				{
					"filename": "climb/Climb_008.png",
					"rotated": false,
					"trimmed": true,
					"sourceSize": {
						"w": 282,
						"h": 464
					},
					"spriteSourceSize": {
						"x": 1,
						"y": 2,
						"w": 271,
						"h": 450
					},
					"frame": {
						"x": 495,
						"y": 924,
						"w": 271,
						"h": 450
					}
				},
				{
					"filename": "climb/Climb_003.png",
					"rotated": false,
					"trimmed": true,
					"sourceSize": {
						"w": 282,
						"h": 464
					},
					"spriteSourceSize": {
						"x": 6,
						"y": 2,
						"w": 272,
						"h": 445
					},
					"frame": {
						"x": 496,
						"y": 459,
						"w": 272,
						"h": 445
					}
				},
				{
					"filename": "climb/Climb_007.png",
					"rotated": false,
					"trimmed": true,
					"sourceSize": {
						"w": 282,
						"h": 464
					},
					"spriteSourceSize": {
						"x": 6,
						"y": 2,
						"w": 272,
						"h": 445
					},
					"frame": {
						"x": 529,
						"y": 1,
						"w": 272,
						"h": 445
					}
				},
				{
					"filename": "throw/Throw__001.png",
					"rotated": false,
					"trimmed": true,
					"sourceSize": {
						"w": 377,
						"h": 451
					},
					"spriteSourceSize": {
						"x": 93,
						"y": 10,
						"w": 242,
						"h": 440
					},
					"frame": {
						"x": 532,
						"y": 1376,
						"w": 242,
						"h": 440
					}
				},
				{
					"filename": "attack/Attack__001.png",
					"rotated": false,
					"trimmed": true,
					"sourceSize": {
						"w": 536,
						"h": 495
					},
					"spriteSourceSize": {
						"x": 46,
						"y": 15,
						"w": 278,
						"h": 439
					},
					"frame": {
						"x": 768,
						"y": 906,
						"w": 278,
						"h": 439
					}
				},
				{
					"filename": "throw/Throw__009.png",
					"rotated": false,
					"trimmed": true,
					"sourceSize": {
						"w": 377,
						"h": 451
					},
					"spriteSourceSize": {
						"x": 96,
						"y": 12,
						"w": 243,
						"h": 439
					},
					"frame": {
						"x": 770,
						"y": 448,
						"w": 243,
						"h": 439
					}
				},
				{
					"filename": "dead/Dead__001.png",
					"rotated": false,
					"trimmed": true,
					"sourceSize": {
						"w": 482,
						"h": 498
					},
					"spriteSourceSize": {
						"x": 7,
						"y": 42,
						"w": 266,
						"h": 435
					},
					"frame": {
						"x": 803,
						"y": 1,
						"w": 266,
						"h": 435
					}
				},
				{
					"filename": "jump/Jump__002.png",
					"rotated": false,
					"trimmed": true,
					"sourceSize": {
						"w": 362,
						"h": 483
					},
					"spriteSourceSize": {
						"x": 43,
						"y": 18,
						"w": 255,
						"h": 435
					},
					"frame": {
						"x": 1015,
						"y": 438,
						"w": 255,
						"h": 435
					}
				},
				{
					"filename": "jump/Jump__003.png",
					"rotated": false,
					"trimmed": true,
					"sourceSize": {
						"w": 362,
						"h": 483
					},
					"spriteSourceSize": {
						"x": 42,
						"y": 18,
						"w": 255,
						"h": 434
					},
					"frame": {
						"x": 1071,
						"y": 1,
						"w": 255,
						"h": 434
					}
				},
				{
					"filename": "jump/Jump__004.png",
					"rotated": false,
					"trimmed": true,
					"sourceSize": {
						"w": 362,
						"h": 483
					},
					"spriteSourceSize": {
						"x": 42,
						"y": 18,
						"w": 255,
						"h": 434
					},
					"frame": {
						"x": 1071,
						"y": 1,
						"w": 255,
						"h": 434
					}
				},
				{
					"filename": "jump/Jump__005.png",
					"rotated": false,
					"trimmed": true,
					"sourceSize": {
						"w": 362,
						"h": 483
					},
					"spriteSourceSize": {
						"x": 42,
						"y": 18,
						"w": 255,
						"h": 434
					},
					"frame": {
						"x": 1071,
						"y": 1,
						"w": 255,
						"h": 434
					}
				},
				{
					"filename": "jump/Jump__006.png",
					"rotated": false,
					"trimmed": true,
					"sourceSize": {
						"w": 362,
						"h": 483
					},
					"spriteSourceSize": {
						"x": 41,
						"y": 18,
						"w": 276,
						"h": 427
					},
					"frame": {
						"x": 776,
						"y": 1347,
						"w": 276,
						"h": 427
					}
				},
				{
					"filename": "throw/Throw__000.png",
					"rotated": false,
					"trimmed": true,
					"sourceSize": {
						"w": 377,
						"h": 451
					},
					"spriteSourceSize": {
						"x": 96,
						"y": 21,
						"w": 259,
						"h": 427
					},
					"frame": {
						"x": 1048,
						"y": 875,
						"w": 259,
						"h": 427
					}
				},
				{
					"filename": "jumpThrow/Jump_Throw__000.png",
					"rotated": false,
					"trimmed": true,
					"sourceSize": {
						"w": 360,
						"h": 431
					},
					"spriteSourceSize": {
						"x": 49,
						"y": 15,
						"w": 299,
						"h": 416
					},
					"frame": {
						"x": 1272,
						"y": 437,
						"w": 299,
						"h": 416
					}
				},
				{
					"filename": "jumpAttack/Jump_Attack__000.png",
					"rotated": false,
					"trimmed": true,
					"sourceSize": {
						"w": 504,
						"h": 522
					},
					"spriteSourceSize": {
						"x": 33,
						"y": 16,
						"w": 298,
						"h": 414
					},
					"frame": {
						"x": 1328,
						"y": 1,
						"w": 298,
						"h": 414
					}
				},
				{
					"filename": "slide/Slide__005.png",
					"rotated": false,
					"trimmed": true,
					"sourceSize": {
						"w": 373,
						"h": 351
					},
					"spriteSourceSize": {
						"x": 17,
						"y": 0,
						"w": 356,
						"h": 349
					},
					"frame": {
						"x": 1628,
						"y": 1,
						"w": 356,
						"h": 349
					}
				},
				{
					"filename": "jumpThrow/Jump_Throw__002.png",
					"rotated": false,
					"trimmed": true,
					"sourceSize": {
						"w": 360,
						"h": 431
					},
					"spriteSourceSize": {
						"x": 48,
						"y": 16,
						"w": 309,
						"h": 402
					},
					"frame": {
						"x": 1628,
						"y": 352,
						"w": 309,
						"h": 402
					}
				},
				{
					"filename": "jumpThrow/Jump_Throw__001.png",
					"rotated": false,
					"trimmed": true,
					"sourceSize": {
						"w": 360,
						"h": 431
					},
					"spriteSourceSize": {
						"x": 49,
						"y": 15,
						"w": 303,
						"h": 410
					},
					"frame": {
						"x": 1573,
						"y": 756,
						"w": 303,
						"h": 410
					}
				},
				{
					"filename": "jumpAttack/Jump_Attack__001.png",
					"rotated": false,
					"trimmed": true,
					"sourceSize": {
						"w": 504,
						"h": 522
					},
					"spriteSourceSize": {
						"x": 33,
						"y": 17,
						"w": 298,
						"h": 413
					},
					"frame": {
						"x": 1054,
						"y": 1304,
						"w": 298,
						"h": 413
					}
				},
				{
					"filename": "jumpAttack/Jump_Attack__002.png",
					"rotated": false,
					"trimmed": true,
					"sourceSize": {
						"w": 504,
						"h": 522
					},
					"spriteSourceSize": {
						"x": 30,
						"y": 20,
						"w": 301,
						"h": 410
					},
					"frame": {
						"x": 1354,
						"y": 1168,
						"w": 301,
						"h": 410
					}
				}
			]
		},
		{
			"image": "sprites-4.png",
			"format": "RGBA8888",
			"size": {
				"w": 1024,
				"h": 1024
			},
			"scale": 1,
			"frames": [
				{
					"filename": "dead/Dead__000.png",
					"rotated": false,
					"trimmed": true,
					"sourceSize": {
						"w": 482,
						"h": 498
					},
					"spriteSourceSize": {
						"x": 19,
						"y": 16,
						"w": 234,
						"h": 452
					},
					"frame": {
						"x": 1,
						"y": 1,
						"w": 234,
						"h": 452
					}
				},
				{
					"filename": "idle/Idle__000.png",
					"rotated": false,
					"trimmed": false,
					"sourceSize": {
						"w": 232,
						"h": 439
					},
					"spriteSourceSize": {
						"x": 0,
						"y": 0,
						"w": 232,
						"h": 439
					},
					"frame": {
						"x": 1,
						"y": 455,
						"w": 232,
						"h": 439
					}
				},
				{
					"filename": "idle/Idle__001.png",
					"rotated": false,
					"trimmed": false,
					"sourceSize": {
						"w": 232,
						"h": 439
					},
					"spriteSourceSize": {
						"x": 0,
						"y": 0,
						"w": 232,
						"h": 439
					},
					"frame": {
						"x": 235,
						"y": 455,
						"w": 232,
						"h": 439
					}
				},
				{
					"filename": "idle/Idle__009.png",
					"rotated": false,
					"trimmed": false,
					"sourceSize": {
						"w": 232,
						"h": 439
					},
					"spriteSourceSize": {
						"x": 0,
						"y": 0,
						"w": 232,
						"h": 439
					},
					"frame": {
						"x": 235,
						"y": 455,
						"w": 232,
						"h": 439
					}
				},
				{
					"filename": "idle/Idle__002.png",
					"rotated": false,
					"trimmed": true,
					"sourceSize": {
						"w": 232,
						"h": 439
					},
					"spriteSourceSize": {
						"x": 2,
						"y": 0,
						"w": 230,
						"h": 439
					},
					"frame": {
						"x": 237,
						"y": 1,
						"w": 230,
						"h": 439
					}
				},
				{
					"filename": "idle/Idle__008.png",
					"rotated": false,
					"trimmed": true,
					"sourceSize": {
						"w": 232,
						"h": 439
					},
					"spriteSourceSize": {
						"x": 2,
						"y": 0,
						"w": 230,
						"h": 439
					},
					"frame": {
						"x": 237,
						"y": 1,
						"w": 230,
						"h": 439
					}
				},
				{
					"filename": "idle/Idle__003.png",
					"rotated": false,
					"trimmed": true,
					"sourceSize": {
						"w": 232,
						"h": 439
					},
					"spriteSourceSize": {
						"x": 3,
						"y": 1,
						"w": 229,
						"h": 438
					},
					"frame": {
						"x": 469,
						"y": 1,
						"w": 229,
						"h": 438
					}
				},
				{
					"filename": "idle/Idle__007.png",
					"rotated": false,
					"trimmed": true,
					"sourceSize": {
						"w": 232,
						"h": 439
					},
					"spriteSourceSize": {
						"x": 3,
						"y": 1,
						"w": 229,
						"h": 438
					},
					"frame": {
						"x": 469,
						"y": 1,
						"w": 229,
						"h": 438
					}
				}
			]
		}
	],
	"meta": {
		"app": "https://www.codeandweb.com/texturepacker",
		"version": "3.0",
		"smartupdate": "$TexturePacker:SmartUpdate:53e8e91ebd2fd360ae9636d540474a74:bfd07b579ecd0a94a7edb1c112855b6f:3e4a539f4e952cdb4da02012c9ef198e$"
	}
}
